aegis/__init__.py
aegis/Core/Config.py
aegis/Core/Plotter.py
aegis/Core/Population.py
aegis/Core/Record.py
aegis/Core/Run.py
aegis/Core/Simulation.py
aegis/Core/__init__.py
aegis/Core/config_default.py
aegis/Core/functions.py
mpi_age_aegis-1.0.data/scripts/aegis
mpi_age_aegis-1.0.dist-info/LICENSE
mpi_age_aegis-1.0.dist-info/METADATA
mpi_age_aegis-1.0.dist-info/WHEEL
mpi_age_aegis-1.0.dist-info/top_level.txt
mpi_age_aegis-1.0.dist-info/RECORD
