Metadata-Version: 2.1
Name: mpi-age-aegis
Version: 1.0
Summary: AEGIS - Ageing of Evolving Genomes In Silico
Home-page: https://github.com/valenzano-lab/aegis
Author: Will Bradshaw, Arian Sajina and Dario Valenzano
Author-email: wbradshaw@age.mpg.de, asajina@age.mpg.de, Dario.Valenzano@age.mpg.de
License: MIT
Platform: UNKNOWN
Requires-Dist: numpy (>=1.15.4)
Requires-Dist: scipy (>=1.1.0)
Requires-Dist: python-dateutil (>=2.7.5)
Requires-Dist: pandas (>=0.23.4)
Requires-Dist: matplotlib (==2.1.0)
Requires-Dist: seaborn (>=0.9.0)
Requires-Dist: pytest (>=4.3.0)
